pyq/__init__.py
pyq/astmatch.py
pyq/pyq.py
pyqtool-0.0.6.dist-info/DESCRIPTION.rst
pyqtool-0.0.6.dist-info/entry_points.txt
pyqtool-0.0.6.dist-info/METADATA
pyqtool-0.0.6.dist-info/metadata.json
pyqtool-0.0.6.dist-info/RECORD
pyqtool-0.0.6.dist-info/top_level.txt
pyqtool-0.0.6.dist-info/WHEEL
sizzle/__init__.py
sizzle/match.py
sizzle/selector.py
