Metadata-Version: 2.0
Name: pyqtool
Version: 0.0.6
Summary: Search Python code using jQuery-like selectors
Home-page: http://github.com/caioariede/pyq
Author: Caio Ariede
Author-email: caio.ariede@gmail.com
License: MIT
Platform: any
Classifier: Intended Audience :: Developers
Classifier: Operating System :: OS Independent
Classifier: License :: OSI Approved :: MIT License
Classifier: Programming Language :: Python
Classifier: Programming Language :: Python :: 3
Classifier: Programming Language :: Python :: 3.4
Requires-Dist: click (==6.2)
Requires-Dist: Pygments (==2.1)
Requires-Dist: regex (==2016.1.10)
Requires-Dist: astor (==0.5)
